CHANGES.rst
LICENSE
ez_setup.py
setup.cfg
setup.py
pyramid_urbanairship/__init__.py
pyramid_urbanairship/tests.py
pyramid_urbanairship.egg-info/PKG-INFO
pyramid_urbanairship.egg-info/SOURCES.txt
pyramid_urbanairship.egg-info/dependency_links.txt
pyramid_urbanairship.egg-info/requires.txt
pyramid_urbanairship.egg-info/top_level.txt