Metadata-Version: 1.0
Name: pyramid-urbanairship
Version: 0.0.2
Summary: Urban airship client library for Pyramid
Home-page: UNKNOWN
Author: UNKNOWN
Author-email: UNKNOWN
License: UNKNOWN
Platform: UNKNOWN
